{
  "itemIdentifier": "ogc.bbr.cco.extended-relation",
  "name": "Common Core Ontology - Extended Relation Ontology",
  "abstract": "CCO Extended Relation Ontology defines Additional relations beyond BFO",
  "status": "under-development",
  "dateTimeAddition": "2025-01-24T00:00:00Z",
  "itemClass": "schema",
  "register": "ogc-building-block",
  "version": "2.0",
  "dateOfLastChange": "2024-11-06",
  "sources": [
    {
      "title": "Common Core Ontologies",
      "link": "https://github.com/CommonCoreOntology/CommonCoreOntologies"
    }
  ],
  "scope": "unstable",
  "tags": [
    "ontology",
    "extended",
    "relation"
  ],
  "shaclRules": [],
  "sourceSchema": "https://raw.githubusercontent.com/ogcincubator/bblocks-cco/main/_sources/extended-relation/schema.yaml",
  "sourceFiles": "https://raw.githubusercontent.com/ogcincubator/bblocks-cco/main/_sources/extended-relation/",
  "group": "Common Core Ontologies",
  "dependsOn": [
    "ogc.bbr.cco.extended-relation.classes.Relation",
    "ogc.bbr.cco.extended-relation.classes.SpatialRelation"
  ],
  "highlighted": true
}
